textprint/__init__.py
textprint/patterns/__init__.py
textprint/patterns/ascii.py
textprint/patterns/base.py
textprint/patterns/bitcoin_address.py
textprint/patterns/c_identifier.py
textprint/patterns/coords.py
textprint/patterns/credit_card.py
textprint/patterns/date.py
textprint/patterns/doi.py
textprint/patterns/email.py
textprint/patterns/emoji.py
textprint/patterns/han_unification.py
textprint/patterns/hashtag.py
textprint/patterns/hyphen_word_break.py
textprint/patterns/ip.py
textprint/patterns/jira.py
textprint/patterns/mac_address.py
textprint/patterns/pan_gstin.py
textprint/patterns/password.py
textprint/patterns/pattern_list.py
textprint/patterns/phone_number.py
textprint/patterns/port_number.py
textprint/patterns/semantic_versioning.py
textprint/patterns/ssn.py
textprint/patterns/url.py
textprint/patterns/url_slug.py
textprint/patterns/username.py
textprint/patterns/uuid.py
textprint-0.1.0.dist-info/LICENSE
textprint-0.1.0.dist-info/WHEEL
textprint-0.1.0.dist-info/METADATA
textprint-0.1.0.dist-info/RECORD
