Metadata-Version: 2.1
Name: textprint
Version: 0.1.0
Summary: Regex patterns. Simplified.
Author: Shadi Boomi
Author-email: shadi.boomi@gmail.com
Requires-Python: >=3.9,<4.0
Classifier: Programming Language :: Python :: 3
Classifier: Programming Language :: Python :: 3.10
Classifier: Programming Language :: Python :: 3.9
